Metadata-Version: 2.1
Name: tkfab
Version: 1.8
Summary: fast user fabric3
Home-page: UNKNOWN
Author: TimHuang
Author-email: 1400471035@qq.com
License: Apache License
Platform: UNKNOWN
Classifier: Environment :: Web Environment
Classifier: Intended Audience :: Developers
Classifier: Operating System :: OS Independent
Classifier: Topic :: Text Processing :: Indexing
Classifier: Topic :: Utilities
Classifier: Topic :: Internet
Classifier: Topic :: Software Development :: Libraries :: Python Modules
Classifier: Programming Language :: Python
Classifier: Programming Language :: Python :: 3.7
